controller_companion/__init__.py
controller_companion/app/__init__.py
controller_companion/app/app.py
controller_companion/app/autostart.py
controller_companion/app/controller_layouts.py
controller_companion/app/popup_about.py
controller_companion/app/popup_create_action.py
controller_companion/app/res/app.png
controller_companion/app/res/playstation/Circle.png
controller_companion/app/res/playstation/Cross.png
controller_companion/app/res/playstation/Down.png
controller_companion/app/res/playstation/L-Stick.png
controller_companion/app/res/playstation/L1.png
controller_companion/app/res/playstation/Left.png
controller_companion/app/res/playstation/Options.png
controller_companion/app/res/playstation/PS.png
controller_companion/app/res/playstation/R-Stick.png
controller_companion/app/res/playstation/R1.png
controller_companion/app/res/playstation/Right.png
controller_companion/app/res/playstation/Share.png
controller_companion/app/res/playstation/Square.png
controller_companion/app/res/playstation/Touch_Pad.png
controller_companion/app/res/playstation/Triangle.png
controller_companion/app/res/playstation/Up.png
controller_companion/app/res/playstation_controller_layout.png
controller_companion/app/res/plus.png
controller_companion/app/res/tray_icon.svg
controller_companion/app/res/tray_icon_16.png
controller_companion/app/res/tray_icon_32.png
controller_companion/app/res/xbox/A.png
controller_companion/app/res/xbox/B.png
controller_companion/app/res/xbox/Back.png
controller_companion/app/res/xbox/Down.png
controller_companion/app/res/xbox/L-Stick.png
controller_companion/app/res/xbox/LB.png
controller_companion/app/res/xbox/Left.png
controller_companion/app/res/xbox/R-Stick.png
controller_companion/app/res/xbox/RB.png
controller_companion/app/res/xbox/Right.png
controller_companion/app/res/xbox/Share.png
controller_companion/app/res/xbox/Start.png
controller_companion/app/res/xbox/Up.png
controller_companion/app/res/xbox/X-Box.png
controller_companion-0.7.6.dist-info/LICENSE
controller_companion-0.7.6.dist-info/METADATA
controller_companion-0.7.6.dist-info/WHEEL
controller_companion-0.7.6.dist-info/entry_points.txt
controller_companion-0.7.6.dist-info/RECORD
