Metadata-Version: 2.3
Name: controller-companion
Version: 0.7.6
Summary: Python app for assigning shortcut actions to game controllers.
Author: Johannes Gundlach
Author-email: 24914225+Johannes11833@users.noreply.github.com
Requires-Python: >=3.9,<3.14
Classifier: Programming Language :: Python :: 3
Classifier: Programming Language :: Python :: 3.9
Classifier: Programming Language :: Python :: 3.10
Classifier: Programming Language :: Python :: 3.11
Classifier: Programming Language :: Python :: 3.12
Classifier: Programming Language :: Python :: 3.13
Requires-Dist: pillow (>=11.0.0,<12.0.0)
Requires-Dist: pyautogui (>=0.9.54,<0.10.0)
Requires-Dist: pygame (>=2.6.1,<3.0.0)
Requires-Dist: pystray (>=0.19.5,<0.20.0)
Requires-Dist: requests (>=2.32.3,<3.0.0)
Requires-Dist: rich (>=13.9.4,<14.0.0)
